setup.py
MarkovTextGenerator/__init__.py
MarkovTextGenerator/markov_text_generator.py
MarkovTextGenerator.egg-info/PKG-INFO
MarkovTextGenerator.egg-info/SOURCES.txt
MarkovTextGenerator.egg-info/dependency_links.txt
MarkovTextGenerator.egg-info/requires.txt
MarkovTextGenerator.egg-info/top_level.txt