Metadata-Version: 1.2
Name: MarkovTextGenerator
Version: 1.6.12
Summary: Generator of pseudo-random text, using Markov chains.
Home-page: https://github.com/NyashniyVladya/MarkovTextGenerator
Author: Vladya
Author-email: UNKNOWN
License: UNKNOWN
Keywords: vladya markovgenerator markov_generator markov_chain MarkovTextGenerator
Platform: UNKNOWN
Classifier: Natural Language :: Russian
Classifier: Programming Language :: Python :: 3.6
Classifier: Programming Language :: Python :: 3.7
Classifier: License :: OSI Approved :: GNU General Public License v3 (GPLv3)
Requires-Python: >=3.6
